gdbundle_plot/__init__.py
gdbundle_plot/gdb_loader.py
gdbundle_plot/lldb_loader.py
gdbundle_plot/scripts/plot_gdb.py
gdbundle_plot/scripts/plot_lldb.py
gdbundle_plot-0.0.5.dist-info/WHEEL
gdbundle_plot-0.0.5.dist-info/METADATA
gdbundle_plot-0.0.5.dist-info/RECORD
